reduce_ex.py
reduce_ex-0.1.0a0.dist-info/licenses/LICENSE
reduce_ex-0.1.0a0.dist-info/METADATA
reduce_ex-0.1.0a0.dist-info/WHEEL
reduce_ex-0.1.0a0.dist-info/top_level.txt
reduce_ex-0.1.0a0.dist-info/RECORD
