Metadata-Version: 2.4
Name: reduce-ex
Version: 0.1.0a0
Summary: n-ary reduce operator with support for prefix/suffix elements. Intermediate results are yielded as well. Like `functools.reduce` but more powerful.
Author-email: Jifeng Wu <jifengwu2k@gmail.com>
License-Expression: MIT
Project-URL: Homepage, https://github.com/jifengwu2k/reduce-ex
Project-URL: Bug Tracker, https://github.com/jifengwu2k/reduce-ex/issues
Classifier: Programming Language :: Python :: 2
Classifier: Programming Language :: Python :: 3
Classifier: Operating System :: OS Independent
Requires-Python: >=2
License-File: LICENSE
Dynamic: license-file
